<annotation>
	<folder>data_images</folder>
	<filename>00242.jpg</filename>
	<path>D:\YOLO\object_detection\1_datapreparation\data_images\00242.jpg</path>
	<source>
		<database>Unknown</database>
	</source>
	<size>
		<width>2048</width>
		<height>1592</height>
		<depth>3</depth>
	</size>
	<segmented>0</segmented>
	<object>
		<name>cat</name>
		<pose>Unspecified</pose>
		<truncated>1</truncated>
		<difficult>0</difficult>
		<bndbox>
			<xmin>195</xmin>
			<ymin>90</ymin>
			<xmax>1716</xmax>
			<ymax>1592</ymax>
		</bndbox>
	</object>
</annotation>
